pasts/__init__.py
pasts/metrics.py
pasts/model.py
pasts/operations.py
pasts/signal.py
pasts/statistical_tests.py
pasts/validation.py
pasts/visualization.py
pasts-2023.3.1.dist-info/LICENSE
pasts-2023.3.1.dist-info/METADATA
pasts-2023.3.1.dist-info/WHEEL
pasts-2023.3.1.dist-info/RECORD
